LICENSE
MANIFEST.in
README.md
requirements.txt
setup.py
gears_babel/__init__.py
gears_babel/compiler.js
gears_babel/compiler.py
gears_babel.egg-info/PKG-INFO
gears_babel.egg-info/SOURCES.txt
gears_babel.egg-info/dependency_links.txt
gears_babel.egg-info/requires.txt
gears_babel.egg-info/top_level.txt
gears_babel/node_modules/.bin/6to5
gears_babel/node_modules/.bin/6to5-node
gears_babel/node_modules/.bin/6to5-runtime
gears_babel/node_modules/.bin/babel
gears_babel/node_modules/.bin/babel-external-helpers
gears_babel/node_modules/.bin/babel-node
gears_babel/node_modules/babel/CHANGELOG-6to5.md
gears_babel/node_modules/babel/CHANGELOG.md
gears_babel/node_modules/babel/CODE_OF_CONDUCT.md
gears_babel/node_modules/babel/CONTRIBUTING.md
gears_babel/node_modules/babel/LICENSE
gears_babel/node_modules/babel/README.md
gears_babel/node_modules/babel/browser-polyfill.js
gears_babel/node_modules/babel/browser.js
gears_babel/node_modules/babel/external-helpers.js
gears_babel/node_modules/babel/package.json
gears_babel/node_modules/babel/polyfill.js
gears_babel/node_modules/babel/register.js
gears_babel/node_modules/babel/templates.json
gears_babel/node_modules/babel/bin/_babel-node
gears_babel/node_modules/babel/bin/babel-external-helpers
gears_babel/node_modules/babel/bin/babel-node
gears_babel/node_modules/babel/bin/babel/dir.js
gears_babel/node_modules/babel/bin/babel/file.js
gears_babel/node_modules/babel/bin/babel/index.js
gears_babel/node_modules/babel/bin/babel/util.js
gears_babel/node_modules/babel/bin/deprecated/6to5
gears_babel/node_modules/babel/bin/deprecated/6to5-node
gears_babel/node_modules/babel/bin/deprecated/6to5-runtime
gears_babel/node_modules/babel/node_modules/.bin/detect-indent
gears_babel/node_modules/babel/node_modules/.bin/leven
gears_babel/node_modules/babel/node_modules/.bin/regenerator-babel
gears_babel/node_modules/babel/node_modules/.bin/regexpu
gears_babel/node_modules/babel/node_modules/.bin/repeating
gears_babel/node_modules/babel/node_modules/acorn-babel/.editorconfig
gears_babel/node_modules/babel/node_modules/acorn-babel/.gitattributes
gears_babel/node_modules/babel/node_modules/acorn-babel/.npmignore
