Metadata-Version: 1.1
Name: gears-babel
Version: 0.1
Summary: Gears compiler for Babel (previously 6to5) http://babeljs.io/
Home-page: https://github.com/mandx/gears-babel
Author: Armando Perez Marques
Author-email: gmandx@gmail.com
License: ISC
Platform: UNKNOWN
Classifier: Development Status :: 3 - Alpha
Classifier: Intended Audience :: Developers
Classifier: Operating System :: OS Independent
Classifier: Programming Language :: Python
Classifier: Programming Language :: Python :: 2.7
Classifier: Programming Language :: Python :: 3.2
